redisimnest/__init__.py
redisimnest/base_cluster.py
redisimnest/base_cluster.pyi
redisimnest/exceptions.py
redisimnest/key.py
redisimnest/key.pyi
redisimnest/pipeline.py
redisimnest/pipeline.pyi
redisimnest/py.typed
redisimnest/settings.py
redisimnest/utils/__init__.py
redisimnest/utils/de_serialization.py
redisimnest/utils/logging.py
redisimnest/utils/misc.py
redisimnest/utils/prefix.py
redisimnest/utils/redis.py
redisimnest/utils/redis_client.py
redisimnest-0.10.0.dist-info/METADATA
redisimnest-0.10.0.dist-info/WHEEL
redisimnest-0.10.0.dist-info/licenses/LICENSE
redisimnest-0.10.0.dist-info/RECORD
