Metadata-Version: 2.4
Name: redisimnest
Version: 0.10.0
Summary: (Redis Imaginary Nesting) brings poetic structure to Redis with elegant, nestable clusters—turning your keyspace into a meaningful, typed, and navigable hierarchy.
Project-URL: Homepage, https://github.com/ruhiddin/redisimnest
Project-URL: Documentation, https://github.com/ruhiddin/redisimnest
Author-email: Ruhiddin Turdaliyev <niddihur@gmail.com>
License: MIT
License-File: LICENSE
Requires-Python: >=3.8
Requires-Dist: pytest>=8.3.5
Requires-Dist: redis>=5.0.0
Provides-Extra: bcrypt
Requires-Dist: bcrypt; extra == 'bcrypt'
Provides-Extra: crypto
Requires-Dist: cryptography; extra == 'crypto'
